Metadata-Version: 1.0
Name: xc
Version: 0.9
Summary: xc is a simple command-line calculator with hex conversions
Home-page: https://github.com/dustmop/xc
Author: Dustin Long
Author-email: me@dustmop.io
License: GPL3
Keywords: hex hexadecimal calc calculator command-line commandline
Platform: UNKNOWN
